pulser_pasqal/__init__.py
pulser_pasqal/_version.py
pulser_pasqal/backends.py
pulser_pasqal/ovh.py
pulser_pasqal/pasqal_cloud.py
pulser_pasqal/py.typed
pulser_pasqal-0.20.8.dist-info/licenses/LICENSE
pulser_pasqal-0.20.8.dist-info/METADATA
pulser_pasqal-0.20.8.dist-info/WHEEL
pulser_pasqal-0.20.8.dist-info/top_level.txt
pulser_pasqal-0.20.8.dist-info/RECORD
