Metadata-Version: 2.4
Name: pulser-pasqal
Version: 0.20.8
Summary: A Pulser extension to execute pulse-level sequences on Pasqal backends.
Home-page: https://github.com/pasqal-io/pasqal-cloud
Author: Pulser Development Team
Maintainer: Pasqal Cloud Services
Maintainer-email: pcs@pasqal.io
License: Apache 2.0
Classifier: Development Status :: 3 - Alpha
Classifier: Programming Language :: Python :: 3
Requires-Python: >=3.8
License-File: LICENSE
Requires-Dist: pasqal-cloud==0.20.8
Requires-Dist: pulser-core>=1.6
Requires-Dist: backoff~=2.2
Dynamic: author
Dynamic: classifier
Dynamic: description
Dynamic: description-content-type
Dynamic: home-page
Dynamic: license
Dynamic: license-file
Dynamic: maintainer
Dynamic: maintainer-email
Dynamic: requires-dist
Dynamic: requires-python
Dynamic: summary
